{"id":"process-e44ac8e4-c88c-48de-a2d8-d74c46f800b5","type":"PROCESS","name":"multiprocess","extensions":{"Process_at2zjUes":{"constants":{"ServiceTask_1x2ts02":{"_activiti_dmn_table_":{"value":"multidecision"}}},"mappings":{"Task_0ym2hxo":{"inputs":{"inputText":{"type":"variable","value":"stringvar"},"inputNumber":{"type":"variable","value":"numbervar"},"inputCheckbox":{"type":"variable","value":"booleanvar"},"inputDate":{"type":"variable","value":"datevar"}},"outputs":{"stringvar":{"type":"variable","value":"inputText"},"numbervar":{"type":"variable","value":"inputNumber"},"booleanvar":{"type":"variable","value":"inputCheckbox"},"datevar":{"type":"variable","value":"inputDate"}}},"ServiceTask_1x2ts02":{"inputs":{"inputString":{"type":"variable","value":"stringvar"},"inputInteger":{"type":"variable","value":"numbervar"},"inputBoolean":{"type":"variable","value":"booleanvar"},"inputDate":{"type":"variable","value":"datevar"}},"outputs":{"stringvar":{"type":"variable","value":"outString"},"numbervar":{"type":"variable","value":"outInteger"},"booleanvar":{"type":"variable","value":"outBoolean"},"datevar":{"type":"variable","value":"outDate"}}},"Task_04shfc3":{"inputs":{"outputText":{"type":"variable","value":"stringvar"},"outputNumber":{"type":"variable","value":"numbervar"},"outputCheckbox":{"type":"variable","value":"booleanvar"},"outputDate":{"type":"variable","value":"datevar"}}}},"properties":{"fff89f4b-7ef9-4c7b-b8fc-dd1f654359c2":{"id":"fff89f4b-7ef9-4c7b-b8fc-dd1f654359c2","name":"stringvar","type":"string","value":"","required":false},"37d463c5-24e9-4051-b74c-77b250749bef":{"id":"37d463c5-24e9-4051-b74c-77b250749bef","name":"booleanvar","type":"boolean","required":false},"5518e797-df0c-4ac9-a4a0-b3c1b8875c95":{"id":"5518e797-df0c-4ac9-a4a0-b3c1b8875c95","name":"numbervar","type":"integer","required":false},"e36a7751-1277-446d-a355-7671d8e0b10e":{"id":"e36a7751-1277-446d-a355-7671d8e0b10e","name":"datevar","type":"date","required":false}},"assignments":{"Task_0ym2hxo":{"type":"identity","assignment":"assignee","id":"Task_0ym2hxo"},"Task_04shfc3":{"type":"identity","assignment":"assignee","id":"Task_04shfc3"}}}}}